almax_logger/__init__.py
almax_logger/services/__init__.py
almax_logger/services/fileSystem.py
almax_logger/tests/__init__.py
almax_logger/tests/test_utils.py
tools/__init__.py
tools/utils.py
almax_logger-2.0.1.dist-info/METADATA
almax_logger-2.0.1.dist-info/WHEEL
almax_logger-2.0.1.dist-info/top_level.txt
almax_logger-2.0.1.dist-info/RECORD
