Metadata-Version: 2.1
Name: almax_logger
Version: 2.0.1
Summary: Library with my most used Classes and Methods
Author: AlMax98
Author-email: alihaider.maqsood@gmail.com
Requires-Dist: pytest ==8.2.2
Requires-Dist: setuptools ==70.2.0
